deepmatch_torch/__init__.py
deepmatch_torch/callbacks.py
deepmatch_torch/inputs.py
deepmatch_torch/layers/__init__.py
deepmatch_torch/layers/core.py
deepmatch_torch/layers/interaction.py
deepmatch_torch/models/BaseModel.py
deepmatch_torch/models/BaseModel2.py
deepmatch_torch/models/PLBaseModel.py
deepmatch_torch/models/__init__.py
deepmatch_torch/models/dssm.py
deepmatch_torch/models/fm.py
deepmatch_torch/models/mind.py
deepmatch_torch/models/ncf.py
deepmatch_torch/models/youtubednn.py
deepmatch_torch/utils/__init__.py
deepmatch_torch/utils/utils.py
deepmatch_torch-0.0.6.dist-info/LICENSE
deepmatch_torch-0.0.6.dist-info/METADATA
deepmatch_torch-0.0.6.dist-info/WHEEL
deepmatch_torch-0.0.6.dist-info/top_level.txt
deepmatch_torch-0.0.6.dist-info/RECORD
