Metadata-Version: 2.1
Name: deepmatch-torch
Version: 0.0.6
Summary: DeepMatch-Torch is a PyTorch Version deep matching model library for recommendations & advertising. It's easy to train models and to export representation vectors for user and item which can be used for ANN search.
Home-page: https://github.com/bbruceyuan/DeepMatch-Torch
Author: bbruceyuan
Author-email: bruceyuan123@gmail.com
License: MIT License
Download-URL: https://github.com/bbruceyuan/DeepMatch-Torch
Keywords: match,deepmatch_torch,deepmatch-torch,deepmatch-pytorch,deep learning,torch,tensor,pytorch,deepmatch
Platform: UNKNOWN
Classifier: License :: OSI Approved :: Apache Software License
Classifier: Operating System :: OS Independent
Classifier: Intended Audience :: Developers
Classifier: Intended Audience :: Education
Classifier: Intended Audience :: Science/Research
Classifier: Programming Language :: Python :: 3
Classifier: Programming Language :: Python :: 3.7
Classifier: Topic :: Scientific/Engineering
Classifier: Topic :: Scientific/Engineering :: Artificial Intelligence
Classifier: Topic :: Software Development
Classifier: Topic :: Software Development :: Libraries
Classifier: Topic :: Software Development :: Libraries :: Python Modules
Requires-Python: >=2.7,!=3.0.*,!=3.1.*,!=3.2.*,!=3.3.*,!=3.4.*
License-File: LICENSE
Requires-Dist: tqdm
Requires-Dist: sklearn
Requires-Dist: deepctr-torch
Requires-Dist: tensorflow
Requires-Dist: pytorch-lightning
